{
  "video_id": "mR2X391fQu4",
  "video_title": "T5x14: Conan",
  "playlist": "no-entendiste-la-peli",
  "category": "análisis de obra",
  "entities": [
    {
      "surface_form": "Conan el Bárbaro (1982)",
      "canonical_guess": "conan-el-barbaro-1982-film",
      "page_type": "entity_work",
      "domain_primary_guess": "arts.cinema",
      "depth_in_video": "monographic",
      "minutes_estimate": 70,
      "framing_marks": [
        {
          "mark_type": "applied_framework",
          "quote_evidence": "Se anuncia análisis arquetípico de Conan el bárbaro con banda sonora de Churches,"
        },
        {
          "mark_type": "declared_thesis",
          "quote_evidence": "Lo importante es entender la diferencia entre mito del héroe y mito del mago,"
        },
        {
          "mark_type": "internal_structure",
          "quote_evidence": "El secreto del acero es seguir intentándolo una y otra vez,"
        }
      ],
      "assumed_prior": false,
      "is_canonical_external": false,
      "is_in_whitelist_soft": false,
      "exists_in_wiki": false,
      "decision": "promote_new",
      "decision_reason": "Análisis arquetípico monográfico (~70 min) en el formato canónico del canal 'No entendiste la peli'. Cumple §2.3 criterios para entity_work: vídeo dedicado a una obra como caso central del marco arquetípico. La película funciona como vehículo para articular varias tesis del canal: (a) la pregunta nuclear 'el secreto del acero' como MacGuffin de virtud-interior (el secreto real NO es la técnica del acero sino el seguir intentándolo + buscar virtud dentro); (b) cartografía elemental aplicada — espada=aire/intelecto, fuego=emociones, tierra=cuerpo/bienes, agua=espíritu/magia; (c) OPOSICIÓN OPERATIVA héroe-vs-mago articulada explícitamente como tesis del canal (acero/autodominio vs báculo/dominio sobre otros); (d) la rueda del dolor como imagen del trauma sin elaboración + foso de las bestias como cristalización del trauma en violencia; (e) lectura crítica de la película misma — 'mejores intenciones arquetípicas que destreza arquetípica', llena de Fiats/deus ex machina; (f) la crucifixión + retorno como ejercis del mito del héroe sin miedo a la muerte; (g) la espada quebrada + venganza vacía como diagnóstico del héroe que confunde destino con venganza. La página debe seguir el formato establecido en entity_work films del wiki (fight-club-1999-film, matrix-1999-film, nosferatu-2024-film, dracula-1992-film, etc.). Relations principales esperables: exemplifies→viaje-heroe, exemplifies→mito-del-mago (canal articula la opposición), exemplifies→trauma-en-proxy (rueda del dolor), exemplifies→adgrediere-masculino ('seguir intentándolo'), references→cuatro-elementos-arquetipicos (espada=aire, etc.), references→dragon-arquetipo (la serpiente como pasión devoradora), references→shadow-archetype, exemplifies→heroe-truncado (Conan queda inconcluso al final), references→bueno-gustavo (caverna interior + recuerda quién eres como pieza arquetípica del Rey León/Hamlet). Sub-agente posterior construye stub completo con frontmatter rico, body estructurado por bloques temáticos del análisis, citas literales del vídeo y wikilinks tipados.",
      "quote_evidence": "Se anuncia análisis arquetípico de Conan el bárbaro con banda sonora de Churches,"
    },
    {
      "surface_form": "héroe vs mago / oposición operativa",
      "canonical_guess": "mito-del-mago",
      "page_type": "concept",
      "domain_primary_guess": "humanities.religion",
      "depth_in_video": "central_thesis",
      "minutes_estimate": 20,
      "framing_marks": [
        {
          "mark_type": "applied_framework",
          "quote_evidence": "El mago no rige el mundo: lo domina para sí, consume a otros por sus pasiones,"
        },
        {
          "mark_type": "internal_structure",
          "quote_evidence": "El báculo del mago porta fuego mágico: capacidad de encender pasiones,"
        }
      ],
      "assumed_prior": true,
      "is_canonical_external": false,
      "is_in_whitelist_soft": false,
      "exists_in_wiki": true,
      "decision": "update_existing",
      "decision_reason": "Refinamiento sustantivo del marco mito-del-mago no presente en la página actual. El cuerpo leído cubre el mago como figura faústica de obsesión por la pérdida (caso Padre Ikari en Evangelion) + creación del gólem como sustituto + contraste espacial con viaje-heroe (el héroe sale, el mago se encierra). El vídeo Conan añade dimensión COMPLEMENTARIA ausente: la OPOSICIÓN OPERATIVA explícita entre el héroe y el mago en el campo del poder. Material nuevo: (a) el báculo del fuego mágico (encender pasiones ajenas) frente a la espada del aire (autodominio + virtud); (b) doctrina invertida del mago 'el poder del acero no es nada, lo que importa es la carne' como articulación canónica del polo mágico; (c) mecanismo de autoconsumo: 'obrar por deseo nos vuelve solo deseo' + el mago transformado en serpiente como destino estructural del que opera vía consumo de otros; (d) criterio del autodominio: 'el autodominio es la diferencia entre el ser fuerte y el ser más fuerte que los demás' — el héroe NO compite por dominar (operación mágica), busca ser fuerte en sí; (e) el verdadero secreto del acero como camino interior ('seguir intentándolo una y otra vez', 'buscar virtud dentro') — conexión con adgrediere. Es articulación canónica del POLO INVERTIDO del mago en clave moral-operativa, complementaria a la lectura cosmológica-faústica ya documentada.",
      "quote_evidence": "El báculo del mago porta fuego mágico: capacidad de encender pasiones,"
    }
  ],
  "pending_updates": [
    {
      "page_id": "mito-del-mago",
      "update_type": "insert_before_passage",
      "anchor_passage": "## Lagunas",
      "content_proposed": "\n\n## La oposición operativa héroe vs mago en Conan el Bárbaro\n\nT5x14 (abr-2026) articula explícitamente la OPOSICIÓN OPERATIVA entre el héroe y el mago a partir del análisis arquetípico de [[conan-el-barbaro-1982-film]]. Donde la sección 'Estructura arquetípica' contrastaba al mago con el viaje del héroe en clave de inversión espacial (el héroe sale al mundo, el mago se encierra), Conan precisa la diferencia en clave **moral-operativa**: ambos manejan poder, pero el héroe lo dirige hacia el AUTODOMINIO mientras el mago lo dirige hacia el DOMINIO DE OTROS por consumo de sus pasiones.\n\n### El báculo del fuego contra la espada del aire\n\nLa cartografía elemental que el canal aplica al análisis de Conan asigna a cada figura su vehículo arquetípico. La espada del héroe es **aire** — intelecto, virtud, capacidad de poner orden sin dañar. El báculo del mago es **fuego** — pasión, deseo, capacidad de encender lo emocional en el otro y dirigirlo.\n\n> \"El báculo del mago porta fuego mágico: capacidad de encender pasiones\"\n→ [T5x14: Conan (1:00:37)](https://youtu.be/mR2X391fQu4?t=3637)\n\n> \"El mago no rige el mundo: lo domina para sí, consume a otros por sus pasiones\"\n→ [T5x14: Conan (1:00:37)](https://youtu.be/mR2X391fQu4?t=3637)\n\n> \"La serpiente devora desde dentro a quien hace trampa con lo arcano\"\n→ [T5x14: Conan (1:00:37)](https://youtu.be/mR2X391fQu4?t=3637)\n\nLas dos modalidades operan sobre el mismo dominio (el poder de moldear el mundo) pero con direcciones inversas: el héroe corta-y-ordena, el mago enciende-y-consume. La asimetría operativa cierra el contraste — el mago necesita las pasiones ajenas como combustible; el héroe necesita las pasiones propias como territorio a ordenar.\n\n### 'El poder del acero no es nada, lo que importa es la carne': la doctrina invertida del mago\n\nLa articulación canónica del polo mágico en Conan se enuncia como doctrina del mago Thulsa Doom dirigida al héroe capturado:\n\n> \"El mago descubre a Conan: 'El poder del acero no es nada, lo que importa es la carne'\"\n→ [T5x14: Conan (1:05:09)](https://youtu.be/mR2X391fQu4?t=3909)\n\n> \"Con sus ojos azules ordena a una doncella lanzarse al vacío\"\n→ [T5x14: Conan (1:05:09)](https://youtu.be/mR2X391fQu4?t=3909)\n\nLa doctrina opera rechazando el acero (intelecto, virtud, civilización) y depositando el poder en la carne (deseo, pasión, control de la voluntad ajena). La eficacia es real — la doncella se lanza al vacío por orden del mago — pero el costo es estructural: la operación consume por dentro al que la ejerce. La pieza enlaza con la lectura ya documentada del gólem como recuerdo confabulado: el mago captura formas exteriores (la voluntad de la doncella, los 27 años de Yui) pero no la vida misma.\n\n### Obrar por deseo nos vuelve solo deseo: el mecanismo de autoconsumo\n\nLa consecuencia ontológica del polo mágico se articula con precisión cuando el mago se transforma físicamente en serpiente al final del film:\n\n> \"El mago se convierte en serpiente: obrar por deseo nos vuelve solo deseo\"\n→ [T5x14: Conan (1:08:41)](https://youtu.be/mR2X391fQu4?t=4121)\n\n> \"Las doncellas se sumergen en una bola de placeres carnales\"\n→ [T5x14: Conan (1:08:41)](https://youtu.be/mR2X391fQu4?t=4121)\n\nEl sujeto que opera por deseo se convierte estructuralmente en deseo. El mago transformado en serpiente cifra el destino del que ha hecho del consumo de otros su modo de operar — la imagen ctónica del [[dragon-arquetipo|dragón devorador]] es ahora su forma real, no metáfora. La conexión con la sección 'El golem como producto estructural del mago' añade un flanco: el gólem es lo que el mago PRODUCE (vida artificial bajo control); la serpiente es lo que el mago LLEGA A SER (encarnación de la pasión que ha estado manipulando en otros).\n\n### El autodominio como diferencia entre fuerte y más fuerte\n\nLa precisión moral del héroe que distingue su modalidad de la del mago se enuncia como sentencia operativa:\n\n> \"El autodominio es la diferencia entre el ser fuerte y el ser más fuerte que los demás\"\n→ [T5x14: Conan (1:02:38)](https://youtu.be/mR2X391fQu4?t=3758)\n\nEl héroe NO compite por ser más fuerte que los demás — operación que requeriría dominarlos vía la modalidad del mago (consumir su voluntad). El héroe busca ser fuerte EN SÍ — autodominio sobre sus propias pasiones. La pieza articula el polo positivo de la oposición: 'ser fuerte' (heroico) ≠ 'ser más fuerte que los demás' (mágico). El segundo requiere los otros como medida; el primero solo requiere uno mismo.\n\n### El verdadero secreto del acero: continuar el camino\n\nEl cierre del bloque mago-vs-héroe en Conan articula la tesis afirmativa del polo heroico — el secreto del acero NO es la técnica civilizatoria que la película presenta como MacGuffin, sino el camino interior del autodominio sostenido:\n\n> \"El secreto del acero es seguir intentándolo una y otra vez\"\n→ [T5x14: Conan (1:11:43)](https://youtu.be/mR2X391fQu4?t=4303)\n\n> \"Es buscar la virtud dentro de uno mismo, no en la espada exterior\"\n→ [T5x14: Conan (1:11:43)](https://youtu.be/mR2X391fQu4?t=4303)\n\nLa consecuencia editorial cierra la oposición operativa: donde el mago se condena al consumo de otros por dejar de buscar la virtud dentro, el héroe sostiene el camino del acero precisamente porque lo entiende como camino interior — el acero exterior es vehículo de la virtud interior, no la virtud misma. La conexión con [[adgrediere-masculino]] es directa: el adgrediere genuino del varón ('seguir intentándolo una y otra vez') es la modalidad heroica del avance contra resistencia, frente a la modalidad mágica del dominio sobre otros que no requiere avanzar — el mago se queda quieto manipulando, el héroe se mueve trabajándose.\n",
      "section_target": null,
      "supersedes_laguna_text": null,
      "wikilinks_introduced": [
        "conan-el-barbaro-1982-film",
        "dragon-arquetipo",
        "adgrediere-masculino"
      ],
      "citations_added": [
        {
          "video_id": "mR2X391fQu4",
          "timestamp_seconds": 3637,
          "cite_markdown": "[T5x14: Conan (1:00:37)](https://youtu.be/mR2X391fQu4?t=3637)"
        },
        {
          "video_id": "mR2X391fQu4",
          "timestamp_seconds": 3758,
          "cite_markdown": "[T5x14: Conan (1:02:38)](https://youtu.be/mR2X391fQu4?t=3758)"
        },
        {
          "video_id": "mR2X391fQu4",
          "timestamp_seconds": 3909,
          "cite_markdown": "[T5x14: Conan (1:05:09)](https://youtu.be/mR2X391fQu4?t=3909)"
        },
        {
          "video_id": "mR2X391fQu4",
          "timestamp_seconds": 4121,
          "cite_markdown": "[T5x14: Conan (1:08:41)](https://youtu.be/mR2X391fQu4?t=4121)"
        },
        {
          "video_id": "mR2X391fQu4",
          "timestamp_seconds": 4303,
          "cite_markdown": "[T5x14: Conan (1:11:43)](https://youtu.be/mR2X391fQu4?t=4303)"
        }
      ],
      "rationale": "Update sustantivo que añade dimensión complementaria al marco mito-del-mago. La página actual articula al mago como figura cosmológico-existencial (Fausto obsesionado por la pérdida + Padre Ikari + producción de gólem); este vídeo articula al mago como figura moral-operativa en oposición explícita al héroe. La nueva sección estructura cinco sub-bloques: (1) el báculo del fuego vs la espada del aire como vehículos elementales arquetípicos; (2) la doctrina invertida del mago ('el poder del acero no es nada, lo que importa es la carne'); (3) el mecanismo de autoconsumo ('obrar por deseo nos vuelve solo deseo' + transformación física en serpiente); (4) el autodominio como criterio diferencial del héroe; (5) el verdadero secreto del acero como camino interior. Las cinco piezas son canónicas de la articulación del canal sobre la oposición héroe-mago — no aparecían en la página y completan el flanco moral-operativo. Anchor 'insert_before_passage' con '## Lagunas' (línea 116 verificada como única ocurrencia) ubica la sección al final del cuerpo prosa.",
      "editorial_intent": "extend"
    }
  ],
  "thesis_candidates": [],
  "discarded": [
    {
      "surface_form": "tienda online Spreadshop (sudaderas, camisetas, grimorios, diseño de patos)",
      "reason_code": "promo",
      "reason_detail": "Promoción comercial de productos propios del canal (sudaderas, camisetas, grimorios) con mención al trabajo de vectorización de Claudia. Filtro topic_filters.json patrón 'promoción/patrocinador/merchandising' aplica directamente.",
      "quote_evidence": "Presentación de la tienda online del canal en Spreadshop (sudaderas, camisetas, grimorios, diseño de patos), trabajo de vectorización hecho por Claudia",
      "review_priority": "low",
      "review_priority_reason": null,
      "enriches_concept": null
    },
    {
      "surface_form": "proyecto Dedalus: piezas AliExpress + carcasa Hellraiser",
      "reason_code": "meta_canal",
      "reason_detail": "Detalle técnico-logístico sobre el proyecto Dédalus/Pandora (piezas de AliExpress, presupuesto bajo 100€, carcasa tipo cubo de Hellraiser, wifi y Bluetooth integrados). La sustancia conceptual sobre Dédalus + Pandora ya está capturada en cibernetica-biosintetica-y-transhumanismo-en-proxy sección H (vía T5x18). Este bullet es detalle de implementación. Nota: contradicción aparente con T5x18 que articulaba Pandora Cero SIN wifi/Bluetooth — aquí menciona 'wifi y Bluetooth integrados', posible iteración posterior del diseño o referencia a Dédalus genérico vs Pandora Cero específicamente. Cualquier discrepancia técnica se resuelve en documentación del proyecto, no en wiki.",
      "quote_evidence": "Proyecto Dedalus: piezas de AliExpress, presupuesto bajo 100€, carcasa tipo cubo de Hellraiser, wifi y Bluetooth integrados",
      "review_priority": "medium",
      "review_priority_reason": "Contradicción aparente con T5x18 (Pandora Cero sin wifi/Bluetooth por seguridad de datos) merece verificación: ¿es Dédalus distinto de Pandora Cero, o iteración del diseño, o cambio de decisión? La nota en cibernetica-biosintetica-y-transhumanismo-en-proxy sobre Pandora Cero sin conectividad inalámbrica podría requerir caveat sobre versiones.",
      "enriches_concept": "cibernetica-biosintetica-y-transhumanismo-en-proxy"
    },
    {
      "surface_form": "banda sonora de Churches",
      "reason_code": "passing_mention",
      "reason_detail": "Referencia a la banda sonora del análisis (música de fondo elegida por el canal para el vídeo). Material decorativo del formato, no contenido temático.",
      "quote_evidence": "Se anuncia análisis arquetípico de Conan el bárbaro con banda sonora de Churches,",
      "review_priority": "low",
      "review_priority_reason": null,
      "enriches_concept": null
    },
    {
      "surface_form": "Schwarzenegger tiene solo dos o tres líneas reales de diálogo",
      "reason_code": "passing_mention",
      "reason_detail": "Observación trivia sobre la película (la economía dialogal de Schwarzenegger en Conan). Anécdota cinéfila que pertenece, si acaso, a la futura página conan-el-barbaro-1982-film como nota lateral, no a entrada propia.",
      "quote_evidence": "Schwarzenegger tiene solo dos o tres líneas reales de diálogo en toda la peli,",
      "review_priority": "low",
      "review_priority_reason": null,
      "enriches_concept": "conan-el-barbaro-1982-film"
    },
    {
      "surface_form": "la película tiene mejores intenciones arquetípicas que destreza arquetípica",
      "reason_code": "passing_mention",
      "reason_detail": "Juicio crítico sobre la película (continuamente llena de Fiats / deus ex machina). Material para el sub-agente que construya el stub de conan-el-barbaro-1982-film como pieza de evaluación arquetípica. No requiere entrada autónoma.",
      "quote_evidence": "La película tiene mejores intenciones arquetípicas que destreza arquetípica,",
      "review_priority": "low",
      "review_priority_reason": null,
      "enriches_concept": "conan-el-barbaro-1982-film"
    },
    {
      "surface_form": "rueda del dolor como trauma sin elaboración",
      "reason_code": "passing_mention",
      "reason_detail": "Imagen central del análisis de Conan (la rueda donde es forjado tras ver morir a su familia). 'La rueda representa la incapacidad de elaborar un dolor incomprensible; Conan se ve forjado en la rueda sin poder desarrollarse de otra forma'. Pieza relevante para el stub de conan-el-barbaro-1982-film como caso de trauma-en-proxy aplicado a obra cinematográfica. No merece entrada autónoma — es lectura simbólica específica de la película, no concepto canal-específico.",
      "quote_evidence": "La rueda representa la incapacidad de elaborar un dolor incomprensible,",
      "review_priority": "low",
      "review_priority_reason": null,
      "enriches_concept": "conan-el-barbaro-1982-film"
    },
    {
      "surface_form": "cabeza de carnero de la espada inspirada en pieza íbera real",
      "reason_code": "passing_mention",
      "reason_detail": "Detalle histórico-arqueológico sobre el diseño de la espada del padre de Conan (inspirada en pieza íbera real). Pertinente para la página conan-el-barbaro-1982-film como nota lateral, no para entrada autónoma.",
      "quote_evidence": "La cabeza de carnero de la espada está inspirada en una pieza íbera real,",
      "review_priority": "low",
      "review_priority_reason": null,
      "enriches_concept": "conan-el-barbaro-1982-film"
    }
  ],
  "blocks_filtered_by_topic_filters": [],
  "_validation_warnings": [
    "DROP framing_mark @ entity[mito-del-mago]: 'El autodominio es la diferencia entre el ser fuerte y el ser'",
    "DROP discarded[la espada quebrada y la venganza vacía] reason=passing_mention quote no literal",
    "DROP discarded[Conan como burro conectado a internet] reason=passing_mention quote no literal"
  ]
}
